{"nodes": [{"id": "d_project_files_pqc_scanner_backend_app_scanners_scapy_probe_py", "label": "scapy_probe.py", "file_type": "code", "source_file": "D:\\Project Files\\PQC_Scanner\\backend\\app\\scanners\\scapy_probe.py", "source_location": "L1"}, {"id": "scanners_scapy_probe_scapyproberesult", "label": "ScapyProbeResult", "file_type": "code", "source_file": "D:\\Project Files\\PQC_Scanner\\backend\\app\\scanners\\scapy_probe.py", "source_location": "L22"}, {"id": "scanners_scapy_probe_scapyproberesult_init", "label": ".__init__()", "file_type": "code", "source_file": "D:\\Project Files\\PQC_Scanner\\backend\\app\\scanners\\scapy_probe.py", "source_location": "L23"}, {"id": "scanners_scapy_probe_build_tls_hello", "label": "_build_tls_hello()", "file_type": "code", "source_file": "D:\\Project Files\\PQC_Scanner\\backend\\app\\scanners\\scapy_probe.py", "source_location": "L54"}, {"id": "scanners_scapy_probe_do_probe", "label": "_do_probe()", "file_type": "code", "source_file": "D:\\Project Files\\PQC_Scanner\\backend\\app\\scanners\\scapy_probe.py", "source_location": "L72"}, {"id": "scanners_scapy_probe_probe_tls_with_pqc_groups", "label": "probe_tls_with_pqc_groups()", "file_type": "code", "source_file": "D:\\Project Files\\PQC_Scanner\\backend\\app\\scanners\\scapy_probe.py", "source_location": "L118"}], "edges": [{"source": "d_project_files_pqc_scanner_backend_app_scanners_scapy_probe_py", "target": "asyncio", "relation": "imports", "confidence": "EXTRACTED", "source_file": "D:\\Project Files\\PQC_Scanner\\backend\\app\\scanners\\scapy_probe.py", "source_location": "L1", "weight": 1.0}, {"source": "d_project_files_pqc_scanner_backend_app_scanners_scapy_probe_py", "target": "logging", "relation": "imports", "confidence": "EXTRACTED", "source_file": "D:\\Project Files\\PQC_Scanner\\backend\\app\\scanners\\scapy_probe.py", "source_location": "L2", "weight": 1.0}, {"source": "d_project_files_pqc_scanner_backend_app_scanners_scapy_probe_py", "target": "socket", "relation": "imports", "confidence": "EXTRACTED", "source_file": "D:\\Project Files\\PQC_Scanner\\backend\\app\\scanners\\scapy_probe.py", "source_location": "L3", "weight": 1.0}, {"source": "d_project_files_pqc_scanner_backend_app_scanners_scapy_probe_py", "target": "concurrent_futures", "relation": "imports_from", "confidence": "EXTRACTED", "source_file": "D:\\Project Files\\PQC_Scanner\\backend\\app\\scanners\\scapy_probe.py", "source_location": "L4", "weight": 1.0}, {"source": "d_project_files_pqc_scanner_backend_app_scanners_scapy_probe_py", "target": "typing", "relation": "imports_from", "confidence": "EXTRACTED", "source_file": "D:\\Project Files\\PQC_Scanner\\backend\\app\\scanners\\scapy_probe.py", "source_location": "L5", "weight": 1.0}, {"source": "d_project_files_pqc_scanner_backend_app_scanners_scapy_probe_py", "target": "scanners_scapy_probe_scapyproberesult", "relation": "contains", "confidence": "EXTRACTED", "source_file": "D:\\Project Files\\PQC_Scanner\\backend\\app\\scanners\\scapy_probe.py", "source_location": "L22", "weight": 1.0}, {"source": "scanners_scapy_probe_scapyproberesult", "target": "scanners_scapy_probe_scapyproberesult_init", "relation": "method", "confidence": "EXTRACTED", "source_file": "D:\\Project Files\\PQC_Scanner\\backend\\app\\scanners\\scapy_probe.py", "source_location": "L23", "weight": 1.0}, {"source": "d_project_files_pqc_scanner_backend_app_scanners_scapy_probe_py", "target": "scanners_scapy_probe_build_tls_hello", "relation": "contains", "confidence": "EXTRACTED", "source_file": "D:\\Project Files\\PQC_Scanner\\backend\\app\\scanners\\scapy_probe.py", "source_location": "L54", "weight": 1.0}, {"source": "d_project_files_pqc_scanner_backend_app_scanners_scapy_probe_py", "target": "scanners_scapy_probe_do_probe", "relation": "contains", "confidence": "EXTRACTED", "source_file": "D:\\Project Files\\PQC_Scanner\\backend\\app\\scanners\\scapy_probe.py", "source_location": "L72", "weight": 1.0}, {"source": "d_project_files_pqc_scanner_backend_app_scanners_scapy_probe_py", "target": "scanners_scapy_probe_probe_tls_with_pqc_groups", "relation": "contains", "confidence": "EXTRACTED", "source_file": "D:\\Project Files\\PQC_Scanner\\backend\\app\\scanners\\scapy_probe.py", "source_location": "L118", "weight": 1.0}, {"source": "scanners_scapy_probe_do_probe", "target": "scanners_scapy_probe_build_tls_hello", "relation": "calls", "confidence": "EXTRACTED", "source_file": "D:\\Project Files\\PQC_Scanner\\backend\\app\\scanners\\scapy_probe.py", "source_location": "L77", "weight": 1.0}, {"source": "scanners_scapy_probe_probe_tls_with_pqc_groups", "target": "scanners_scapy_probe_scapyproberesult", "relation": "calls", "confidence": "EXTRACTED", "source_file": "D:\\Project Files\\PQC_Scanner\\backend\\app\\scanners\\scapy_probe.py", "source_location": "L125", "weight": 1.0}], "raw_calls": [{"caller_nid": "scanners_scapy_probe_build_tls_hello", "callee": "TLS_Ext_SupportedGroups", "source_file": "D:\\Project Files\\PQC_Scanner\\backend\\app\\scanners\\scapy_probe.py", "source_location": "L61"}, {"caller_nid": "scanners_scapy_probe_build_tls_hello", "callee": "TLSClientHello", "source_file": "D:\\Project Files\\PQC_Scanner\\backend\\app\\scanners\\scapy_probe.py", "source_location": "L62"}, {"caller_nid": "scanners_scapy_probe_build_tls_hello", "callee": "bytes", "source_file": "D:\\Project Files\\PQC_Scanner\\backend\\app\\scanners\\scapy_probe.py", "source_location": "L67"}, {"caller_nid": "scanners_scapy_probe_build_tls_hello", "callee": "RuntimeError", "source_file": "D:\\Project Files\\PQC_Scanner\\backend\\app\\scanners\\scapy_probe.py", "source_location": "L69"}, {"caller_nid": "scanners_scapy_probe_do_probe", "callee": "IP", "source_file": "D:\\Project Files\\PQC_Scanner\\backend\\app\\scanners\\scapy_probe.py", "source_location": "L78"}, {"caller_nid": "scanners_scapy_probe_do_probe", "callee": "TCP", "source_file": "D:\\Project Files\\PQC_Scanner\\backend\\app\\scanners\\scapy_probe.py", "source_location": "L78"}, {"caller_nid": "scanners_scapy_probe_do_probe", "callee": "sr1", "source_file": "D:\\Project Files\\PQC_Scanner\\backend\\app\\scanners\\scapy_probe.py", "source_location": "L79"}, {"caller_nid": "scanners_scapy_probe_do_probe", "callee": "get", "source_file": "D:\\Project Files\\PQC_Scanner\\backend\\app\\scanners\\scapy_probe.py", "source_location": "L87"}, {"caller_nid": "scanners_scapy_probe_do_probe", "callee": "hex", "source_file": "D:\\Project Files\\PQC_Scanner\\backend\\app\\scanners\\scapy_probe.py", "source_location": "L87"}, {"caller_nid": "scanners_scapy_probe_do_probe", "callee": "get", "source_file": "D:\\Project Files\\PQC_Scanner\\backend\\app\\scanners\\scapy_probe.py", "source_location": "L89"}, {"caller_nid": "scanners_scapy_probe_do_probe", "callee": "hex", "source_file": "D:\\Project Files\\PQC_Scanner\\backend\\app\\scanners\\scapy_probe.py", "source_location": "L89"}, {"caller_nid": "scanners_scapy_probe_do_probe", "callee": "str", "source_file": "D:\\Project Files\\PQC_Scanner\\backend\\app\\scanners\\scapy_probe.py", "source_location": "L113"}, {"caller_nid": "scanners_scapy_probe_probe_tls_with_pqc_groups", "callee": "get_event_loop", "source_file": "D:\\Project Files\\PQC_Scanner\\backend\\app\\scanners\\scapy_probe.py", "source_location": "L120"}, {"caller_nid": "scanners_scapy_probe_probe_tls_with_pqc_groups", "callee": "wait_for", "source_file": "D:\\Project Files\\PQC_Scanner\\backend\\app\\scanners\\scapy_probe.py", "source_location": "L121"}, {"caller_nid": "scanners_scapy_probe_probe_tls_with_pqc_groups", "callee": "run_in_executor", "source_file": "D:\\Project Files\\PQC_Scanner\\backend\\app\\scanners\\scapy_probe.py", "source_location": "L122"}, {"caller_nid": "scanners_scapy_probe_probe_tls_with_pqc_groups", "callee": "get", "source_file": "D:\\Project Files\\PQC_Scanner\\backend\\app\\scanners\\scapy_probe.py", "source_location": "L129"}, {"caller_nid": "scanners_scapy_probe_probe_tls_with_pqc_groups", "callee": "get", "source_file": "D:\\Project Files\\PQC_Scanner\\backend\\app\\scanners\\scapy_probe.py", "source_location": "L130"}, {"caller_nid": "scanners_scapy_probe_probe_tls_with_pqc_groups", "callee": "get", "source_file": "D:\\Project Files\\PQC_Scanner\\backend\\app\\scanners\\scapy_probe.py", "source_location": "L131"}, {"caller_nid": "scanners_scapy_probe_probe_tls_with_pqc_groups", "callee": "str", "source_file": "D:\\Project Files\\PQC_Scanner\\backend\\app\\scanners\\scapy_probe.py", "source_location": "L145"}]}